dapla_geoio/__init__.py
dapla_geoio/geoparquet.py
dapla_geoio/io.py
dapla_geoio/py.typed
ssb_dapla_geoio-0.2.0.dist-info/LICENSE
ssb_dapla_geoio-0.2.0.dist-info/METADATA
ssb_dapla_geoio-0.2.0.dist-info/WHEEL
ssb_dapla_geoio-0.2.0.dist-info/RECORD
