Metadata-Version: 2.3
Name: ssb-dapla-geoio
Version: 0.2.0
Summary: Dapla GeoIO
License: MIT
Author: Bjørn Lie Rapp
Author-email: bjorn.rapp@ssb.no
Requires-Python: >=3.10,<4.0
Classifier: Development Status :: 2 - Pre-Alpha
Requires-Dist: dapla-toolbelt (>=3.2.2,<4.0.0)
Requires-Dist: gcsfs (>=2025.5.1)
Requires-Dist: geopandas (>=1.0.1,<2.0.0)
Requires-Dist: pyogrio (>=0.10.0,<0.11.0)
Requires-Dist: strenum (>=0.4.15,<0.5.0)
Requires-Dist: universal-pathlib (>=0.2.6)
Project-URL: Changelog, https://github.com/statisticsnorway/dapla-geoio/releases
Project-URL: Documentation, https://statisticsnorway.github.io/dapla-geoio
Project-URL: Homepage, https://github.com/statisticsnorway/dapla-geoio
Project-URL: Repository, https://github.com/statisticsnorway/dapla-geoio
